QuantGaussVector/QGVC.py
QuantGaussVector/QGVR.py
QuantGaussVector/__init__.py
QuantGaussVector-1.0.0.dist-info/LICENSE
QuantGaussVector-1.0.0.dist-info/METADATA
QuantGaussVector-1.0.0.dist-info/WHEEL
QuantGaussVector-1.0.0.dist-info/top_level.txt
QuantGaussVector-1.0.0.dist-info/RECORD
