Metadata-Version: 2.1
Name: QuantGaussVector
Version: 1.0.0
Summary: A deep learning library for Gaussian Process Regression with quantization and vectorization.
Home-page: https://github.com/MM21B038/QuantGaussVector
Author: Manav Gupta
Author-email: manav26102002@gmail.com
Classifier: Programming Language :: Python :: 3
Classifier: License :: OSI Approved :: MIT License
Classifier: Operating System :: OS Independent
Requires-Python: >=3.10
License-File: LICENSE
Requires-Dist: numpy>=1.20
Requires-Dist: scipy>=1.7
Requires-Dist: joblib>=1.0
Provides-Extra: dev
Requires-Dist: jupyter; extra == "dev"
Requires-Dist: ipython; extra == "dev"
Requires-Dist: pytest; extra == "dev"
Requires-Dist: flake8; extra == "dev"
